{"package_name": "foundation", "interface_list": ["Equatable", "Hashable", "RawRepresentable"], "class_inherit_list": [], "Methods": [], "Vars": [{"var_type": "NSTextCheckingKey", "var_description": "A key that corresponds to the airline of a transit result.", "var_name": "airline"}, {"var_type": "NSTextCheckingKey", "var_description": "A key that corresponds to the city component of the address.", "var_name": "city"}, {"var_type": "NSTextCheckingKey", "var_description": "A key that corresponds to the country component of the address.", "var_name": "country"}, {"var_type": "NSTextCheckingKey", "var_description": "A key that corresponds to the flight component of a transit result.", "var_name": "flight"}, {"var_type": "NSTextCheckingKey", "var_description": "A key that corresponds to the job component of the address.", "var_name": "jobTitle"}, {"var_type": "NSTextCheckingKey", "var_description": "A key that corresponds to the name component of the address.", "var_name": "name"}, {"var_type": "NSTextCheckingKey", "var_description": "A key that corresponds to the organization component of the address.", "var_name": "organization"}, {"var_type": "NSTextCheckingKey", "var_description": "A key that corresponds to the phone number component of the address.", "var_name": "phone"}, {"var_type": "NSTextCheckingKey", "var_description": "A key that corresponds to the state or province component of the address.", "var_name": "state"}, {"var_type": "NSTextCheckingKey", "var_description": "A key that corresponds to the street address component of the address.", "var_name": "street"}, {"var_type": "NSTextCheckingKey", "var_description": "A key that corresponds to the zip code or postal code component of the address.", "var_name": "zip"}], "subclass_list": [], "class_description": "", "class_name": "NSTextCheckingKey"}