{"package_name": ["foundat"], "class_name": ["ns", "key", "valu", "chang", "key"], "class_description": ["constant", "use", "key", "chang", "dictionari", "pass", "observevalueforkeypathofchangecontext"], "class_inherit_list": [], "interface_list": [["equat"], ["hashabl"], ["raw", "represent"]], "subclass_list": [], "Methods": [], "Vars": [{"var_name": ["index", "key"], "var_type": ["ns", "key", "valu", "chang", "key"], "var_description": ["valu", "kindkey", "entri", "nskeyvaluechangeinsert", "nskeyvaluechangeremov", "nskeyvaluechangereplac", "valu", "key", "nsindexset", "object", "contain", "index", "insert", "remov", "replac", "object"]}, {"var_name": ["kind", "key"], "var_type": ["ns", "key", "valu", "chang", "key"], "var_description": ["nsnumber", "object", "contain", "valu", "correspond", "one", "nskeyvaluechang", "enum", "indic", "sort", "chang", "occur"]}, {"var_name": ["new", "key"], "var_type": ["ns", "key", "valu", "chang", "key"], "var_description": ["valu", "kindkey", "entri", "nskeyvaluechangeset", "new", "specifi", "observ", "regist", "valu", "key", "new", "valu", "attribut"]}, {"var_name": ["notif", "is", "prior", "key"], "var_type": ["ns", "key", "valu", "chang", "key"], "var_description": ["prior", "option", "specifi", "observ", "regist", "notif", "sent", "prior", "chang"]}, {"var_name": ["old", "key"], "var_type": ["ns", "key", "valu", "chang", "key"], "var_description": ["valu", "kindkey", "entri", "nskeyvaluechangeset", "old", "specifi", "observ", "regist", "valu", "key", "valu", "attribut", "chang"]}]}