{"package_name": ["foundat"], "class_name": ["ns", "uniqu", "id", "specifi"], "class_description": ["specifi", "work", "object", "id", "properti", "uniqu", "id", "object", "pass", "instanc", "nsuniqueidspecifi", "must", "either", "nsnumber", "object", "nsstring", "object", "exact", "type", "match", "script", "dictionari", "declar", "id", "attribut", "relev", "script", "classyou", "expect", "id", "properti", "read", "object", "support", "therefor", "scripter", "obtain", "uniqu", "id", "object", "refer", "object", "id", "set", "uniqu", "idyou", "dont", "normal", "subclass", "nsuniqueidspecifierth", "evalu", "nsuniqueidspecifi", "object", "follow", "step", "specifi", "object", "foundif", "contain", "implement", "method", "whose", "selector", "match", "relev", "valueinkeywithuniqueid", "pattern", "establish", "script", "keyvalu", "code", "method", "invok", "method", "potenti", "fast", "may", "rel", "easi", "implementa", "case", "evalu", "script", "object", "specifi", "contain", "specifi", "object", "given", "chanc", "evalu", "object", "specifi", "contain", "class", "implement", "indicesofobjectsbyevaluatingobjectspecifi", "method", "method", "invok", "method", "potenti", "fast", "rel", "difficult", "implementan", "nswhosespecifi", "object", "specifi", "first", "object", "whose", "relev", "id", "attribut", "match", "id", "synthes", "evalu", "nswhosespecifi", "object", "must", "search", "key", "element", "contain", "look", "match", "search", "potenti", "slow"], "class_inherit_list": [["ns", "script", "object", "specifi"]], "interface_list": [["c", "var", "arg"], ["equat"], ["hashabl"]], "subclass_list": [], "Methods": [], "Vars": [{"var_name": ["uniqu", "id"], "var_type": ["ani"], "var_description": ["return", "id", "encapsul", "receiv"]}]}